[{"_firstName":"Deep","_lastName":"Deep","_address":"hello","_city":"Pune","_state":"Pune","_zip":"457845","_phoneNumber":"8574859674"},{"_firstName":"Shubham","_lastName":"Dukhate","_address":"Majiwada","_city":"Thane","_state":"Maharashtra","_zip":"400601","_phoneNumber":"9999777755"},{"_firstName":"Akshay","_lastName":"Desai","_address":"Mumbai","_city":"Thane","_state":"Maharashtra","_zip":"400525","_phoneNumber":"9922114455"},{"_firstName":"Shubham","_lastName":"Savant","_address":"New Mumbai","_city":"Mahara","_state":"Mahara","_zip":"212155","_phoneNumber":"7777332200"},{"_firstName":"Rohit","_lastName":"Sharma","_address":"Thane","_city":"Mumbai","_state":"Maharashtra","_zip":"528552","_phoneNumber":"8956784512"},{"_firstName":"Xyz","_lastName":"Xyz","_address":"Thane","_city":"Thane","_state":"Thane","_zip":"400604","_phoneNumber":"8652556022"},{"_firstName":"Pratik","_lastName":"Patil","_address":"Wadala","_city":"Mumbai","_state":"Maharashtra","_zip":"252555","_phoneNumber":"8899001100"}]